ideacli/__init__.py
ideacli/add.py
ideacli/cli.py
ideacli/clipboard.py
ideacli/enquire.py
ideacli/files.py
ideacli/importer.py
ideacli/list.py
ideacli/rename.py
ideacli/repository.py
ideacli/rm.py
ideacli/show.py
ideacli/update.py
ideacli-0.1.3.dist-info/licenses/LICENSE
ideacli-0.1.3.dist-info/METADATA
ideacli-0.1.3.dist-info/WHEEL
ideacli-0.1.3.dist-info/entry_points.txt
ideacli-0.1.3.dist-info/top_level.txt
ideacli-0.1.3.dist-info/RECORD
