Metadata-Version: 2.4
Name: ideacli
Version: 0.1.3
Summary: A command-line tool for curating and managing ideas
Author-email: Your Name <ellisiana@gmail.com>
Maintainer-email: Your Name <ellisiana@gmail.com>
License-Expression: GPL-3.0
Project-URL: Homepage, https://github.com/magicalbob/ideacli
Project-URL: Bug Reports, https://github.com/magicalbob/ideacli/issues
Project-URL: Source, https://github.com/magicalbob/ideacli
Keywords: ideas,cli,productivity,notes,brainstorming
Classifier: Development Status :: 4 - Beta
Classifier: Intended Audience :: Developers
Classifier: Topic :: Utilities
Classifier: Programming Language :: Python :: 3
Classifier: Programming Language :: Python :: 3.8
Classifier: Programming Language :: Python :: 3.9
Classifier: Programming Language :: Python :: 3.10
Classifier: Programming Language :: Python :: 3.11
Classifier: Programming Language :: Python :: 3.12
Classifier: Operating System :: OS Independent
Requires-Python: >=3.8
License-File: LICENSE
Requires-Dist: click>=8.0.0
Requires-Dist: rich>=10.0.0
Requires-Dist: pydantic>=2.0.0
Provides-Extra: dev
Requires-Dist: pytest>=6.0.0; extra == "dev"
Requires-Dist: pytest-cov>=2.0.0; extra == "dev"
Requires-Dist: black>=22.0.0; extra == "dev"
Requires-Dist: flake8>=4.0.0; extra == "dev"
Requires-Dist: mypy>=0.910; extra == "dev"
Dynamic: license-file
